thola_nautobot/__init__.py
thola_nautobot/api/__init__.py
thola_nautobot/api/serializers.py
thola_nautobot/api/urls.py
thola_nautobot/api/views.py
thola_nautobot/choices.py
thola_nautobot/forms.py
thola_nautobot/models.py
thola_nautobot/navigation.py
thola_nautobot/tables.py
thola_nautobot/template_content.py
thola_nautobot/templates/thola_nautobot/device_extension.html
thola_nautobot/templates/thola_nautobot/device_extension_disabled.html
thola_nautobot/templates/thola_nautobot/tholaconfig.html
thola_nautobot/templates/thola_nautobot/tholaconfig_edit.html
thola_nautobot/templates/thola_nautobot/tholaconfig_list.html
thola_nautobot/templates/thola_nautobot/tholaonboarding.html
thola_nautobot/templates/thola_nautobot/tholaonboarding_list.html
thola_nautobot/templates/thola_nautobot/tholastatus.html
thola_nautobot/thola/__init__.py
thola_nautobot/thola/client.py
thola_nautobot/thola/snmp_config.py
thola_nautobot/thola/utils.py
thola_nautobot/urls.py
thola_nautobot/views.py
thola_nautobot/worker.py
thola_nautobot-0.2.0.dist-info/LICENSE
thola_nautobot-0.2.0.dist-info/WHEEL
thola_nautobot-0.2.0.dist-info/METADATA
thola_nautobot-0.2.0.dist-info/RECORD
