Metadata-Version: 2.1
Name: thola-nautobot
Version: 0.2.0
Summary: Thola plugin for Nautobot
License: BSD-2-Clause License
Author: Thola Team
Requires-Python: >=3.8,<4.0
Classifier: License :: Other/Proprietary License
Classifier: Programming Language :: Python :: 3
Classifier: Programming Language :: Python :: 3.8
Classifier: Programming Language :: Python :: 3.9
Requires-Dist: nautobot (>=1.0,<1.1)
Requires-Dist: thola-client (>=1.0.2,<2.0.0)
